{"migrated":{"identifier":"migrated","description":"permissions that were migrated from v1","local":true,"windows":["*"],"permissions":["path:default","event:default","window:default","app:default","resources:default","menu:default","tray:default","webview:default","webview:allow-create-webview-window","fs:allow-write-file","window:allow-create","window:allow-center","window:allow-set-minimizable","window:allow-set-closable","window:allow-maximize","window:allow-unmaximize","window:allow-minimize","window:allow-unminimize","window:allow-show","window:allow-hide","window:allow-close","window:allow-set-min-size","window:allow-set-fullscreen","window:allow-set-focus","window:allow-start-dragging","shell:allow-open","dialog:allow-save","clipboard-manager:allow-read-text","app:allow-app-show","app:allow-app-hide","dialog:default","fs:default","fs:write-all","shell:default","clipboard-manager:default"]}}